[
{"_id":"0-1714482830004-392e0881d1bd","title":"Yesterday","snippet":"Can't remember.","body":"I said I can't remember.","createdAt":"2024-04-30T13:13:50.004Z","updatedAt":"2024-04-30T13:13:50.004Z"},
{"_id":"1-1714482867013-6d19dc5e0a33","title":"Today","snippet":"Ask me later.","body":"Didn't I say ask me later?!","createdAt":"2024-04-30T13:14:27.013Z","updatedAt":"2024-04-30T13:14:27.013Z"},
{"_id":"2-1714482876512-15aa68223754","title":"Tomorrow","snippet":"Don't know yet.","body":"What am I, a prophet?! I don't know yet.","createdAt":"2024-04-30T13:14:36.512Z","updatedAt":"2024-04-30T13:14:36.512Z"},
{"_id":"3-1714482888105-47f9c3a3c981","title":"Yoshi's Party","snippet":"Come and have a good time.","body":"sdkjgdasjfdskjf sdjf ksadf jklsdjafkl .","createdAt":"2024-04-30T13:14:48.105Z","updatedAt":"2024-04-30T13:14:48.105Z"},
{"_id":"0-1714551308009-e395ea82e8bb","title":"Story 1","snippet":"A nice story.","body":"This is a nice story about nice people.","createdAt":"2024-05-01T08:15:08.009Z","updatedAt":"2024-05-01T08:15:08.009Z"},
{"_id":"0-1714655899594-a534b87a4084","title":"Woo!","snippet":"Shrek","body":"somebody once told me the world is gonna role me.","createdAt":"2024-05-02T13:18:19.594Z","updatedAt":"2024-05-04T15:24:53.593Z"},
{"_id":"1-1714551357763-ba8f8b8ffd53","title":"Story 2","snippet":"An epic story.","body":"This is an epic story about how Israel became a \r\nmajor power state. ","createdAt":"2024-05-01T08:15:57.763Z","updatedAt":"2024-05-05T11:15:14.996Z"}
]